MANIFEST.in
README.md
csv_to_table.py
requirements.txt
setup.py
csv_to_table.egg-info/PKG-INFO
csv_to_table.egg-info/SOURCES.txt
csv_to_table.egg-info/dependency_links.txt
csv_to_table.egg-info/entry_points.txt
csv_to_table.egg-info/requires.txt
csv_to_table.egg-info/top_level.txt
typeguesser/TypeGuesser.py
typeguesser/__init__.py