Metadata-Version: 1.1
Name: csv-to-table
Version: 0.0.2
Summary: Generates a CREATE TABLE statement from a CSV file by guessing at column types
Home-page: https://github.com/jackmaney/csv_to_table.py.git
Author: Jack Maney
Author-email: jackmaney@gmail.com
License: MIT
Platform: UNKNOWN
Classifier: Development Status :: 3 - Alpha
Classifier: Intended Audience :: Science/Research
Classifier: License :: OSI Approved :: MIT License
Classifier: Programming Language :: Python :: 2 :: Only
Classifier: Topic :: Utilities
